bmcmc/version.py
bmcmc/model.py
bmcmc/__init__.py
bmcmc-0.1.0.dist-info/DESCRIPTION.rst
bmcmc-0.1.0.dist-info/METADATA
bmcmc-0.1.0.dist-info/RECORD
bmcmc-0.1.0.dist-info/WHEEL
bmcmc-0.1.0.dist-info/top_level.txt
bmcmc-0.1.0.dist-info/metadata.json
