Metadata-Version: 2.0
Name: bmcmc
Version: 0.1.0
Summary: An MCMC package for Bayesian data analysis
Home-page: https://github.com/sanjibs/bmcmc
Author: Sanjib Sharma
Author-email: bug.sanjib@gmail.com
License: BSD
Platform: UNKNOWN
Classifier: Development Status :: 4 - Beta
Classifier: Intended Audience :: Science/Research
Classifier: Topic :: Scientific/Engineering
Classifier: License :: OSI Approved :: BSD License
Classifier: Programming Language :: Python :: 2.7
Requires-Dist: ebfpy
